{
  "generated_at_utc": "2025-12-19T18:36:48.525553+00:00",
  "lookback_days": 60,
  "start_date": "2025-10-20",
  "end_date": "2025-12-19",
  "assets": [
    {
      "symbol": "BTC-USD",
      "start_price": 106467.7890625,
      "end_price": 87164.03125,
      "momentum": -0.181311,
      "momentum_pct": "-18.13%"
    },
    {
      "symbol": "ETH-USD",
      "start_price": 3832.558837890625,
      "end_price": 2963.480712890625,
      "momentum": -0.226762,
      "momentum_pct": "-22.68%"
    },
    {
      "symbol": "SOL-USD",
      "start_price": 182.0347900390625,
      "end_price": 124.44559478759766,
      "momentum": -0.316364,
      "momentum_pct": "-31.64%"
    },
    {
      "symbol": "AAPL",
      "start_price": 252.045654296875,
      "end_price": 270.7300109863281,
      "momentum": 0.074131,
      "momentum_pct": "7.41%"
    }
  ]
}