{
  "generated_at_utc": "2026-04-21T23:48:06.437567+00:00",
  "lookback_days": 60,
  "start_date": "2026-02-20",
  "end_date": "2026-04-21",
  "assets": [
    {
      "symbol": "BTC-USD",
      "start_price": 67494.21875,
      "end_price": 76405.7265625,
      "momentum": 0.132034,
      "momentum_pct": "13.20%"
    },
    {
      "symbol": "ETH-USD",
      "start_price": 1992.1943359375,
      "end_price": 2329.7900390625,
      "momentum": 0.169459,
      "momentum_pct": "16.95%"
    },
    {
      "symbol": "SOL-USD",
      "start_price": 85.1976089477539,
      "end_price": 86.08000183105469,
      "momentum": 0.010357,
      "momentum_pct": "1.04%"
    },
    {
      "symbol": "AAPL",
      "start_price": 263.8800048828125,
      "end_price": 266.1700134277344,
      "momentum": 0.008678,
      "momentum_pct": "0.87%"
    }
  ]
}