{
  "generated_at_utc": "2025-09-18T05:53:27.431603+00:00",
  "lookback_days": 60,
  "start_date": "2025-07-20",
  "end_date": "2025-09-18",
  "assets": [
    {
      "symbol": "BTC-USD",
      "start_price": 119289.84375,
      "end_price": 117264.4296875,
      "momentum": -0.016979,
      "momentum_pct": "-1.70%"
    },
    {
      "symbol": "ETH-USD",
      "start_price": 3476.784423828125,
      "end_price": 4587.5478515625,
      "momentum": 0.31948,
      "momentum_pct": "31.95%"
    },
    {
      "symbol": "SOL-USD",
      "start_price": 175.7930450439453,
      "end_price": 244.7887725830078,
      "momentum": 0.392483,
      "momentum_pct": "39.25%"
    },
    {
      "symbol": "AAPL",
      "start_price": 209.78192138671875,
      "end_price": 238.99000549316406,
      "momentum": 0.139231,
      "momentum_pct": "13.92%"
    }
  ]
}