{
  "generated_at_utc": "2025-09-11T21:52:58.363458+00:00",
  "lookback_days": 60,
  "start_date": "2025-07-13",
  "end_date": "2025-09-11",
  "assets": [
    {
      "symbol": "BTC-USD",
      "start_price": 115987.203125,
      "end_price": 114495.8046875,
      "momentum": -0.012858,
      "momentum_pct": "-1.29%"
    },
    {
      "symbol": "ETH-USD",
      "start_price": 2954.84521484375,
      "end_price": 4425.24560546875,
      "momentum": 0.497623,
      "momentum_pct": "49.76%"
    },
    {
      "symbol": "SOL-USD",
      "start_price": 164.06277465820312,
      "end_price": 226.65830993652344,
      "momentum": 0.381534,
      "momentum_pct": "38.15%"
    },
    {
      "symbol": "AAPL",
      "start_price": 212.16920471191406,
      "end_price": 230.02999877929688,
      "momentum": 0.084182,
      "momentum_pct": "8.42%"
    }
  ]
}