{
  "generated_at_utc": "2026-01-05T11:45:28.004706+00:00",
  "lookback_days": 60,
  "start_date": "2025-11-06",
  "end_date": "2026-01-05",
  "assets": [
    {
      "symbol": "BTC-USD",
      "start_price": 106547.5234375,
      "end_price": 92893.96875,
      "momentum": -0.128145,
      "momentum_pct": "-12.81%"
    },
    {
      "symbol": "ETH-USD",
      "start_price": 3602.30810546875,
      "end_price": 3173.7607421875,
      "momentum": -0.118965,
      "momentum_pct": "-11.90%"
    },
    {
      "symbol": "SOL-USD",
      "start_price": 166.0906982421875,
      "end_price": 135.36611938476562,
      "momentum": -0.184987,
      "momentum_pct": "-18.50%"
    },
    {
      "symbol": "AAPL",
      "start_price": 268.7894287109375,
      "end_price": 271.010009765625,
      "momentum": 0.008261,
      "momentum_pct": "0.83%"
    }
  ]
}