{
  "generated_at_utc": "2025-12-29T22:56:48.134079+00:00",
  "lookback_days": 60,
  "start_date": "2025-10-30",
  "end_date": "2025-12-29",
  "assets": [
    {
      "symbol": "BTC-USD",
      "start_price": 114119.328125,
      "end_price": 87262.671875,
      "momentum": -0.235338,
      "momentum_pct": "-23.53%"
    },
    {
      "symbol": "ETH-USD",
      "start_price": 4120.1220703125,
      "end_price": 2936.605224609375,
      "momentum": -0.287253,
      "momentum_pct": "-28.73%"
    },
    {
      "symbol": "SOL-USD",
      "start_price": 198.74171447753906,
      "end_price": 123.3604965209961,
      "momentum": -0.379292,
      "momentum_pct": "-37.93%"
    },
    {
      "symbol": "AAPL",
      "start_price": 268.5496520996094,
      "end_price": 273.760009765625,
      "momentum": 0.019402,
      "momentum_pct": "1.94%"
    }
  ]
}