{
  "generated_at_utc": "2025-11-13T23:52:48.461122+00:00",
  "lookback_days": 60,
  "start_date": "2025-09-14",
  "end_date": "2025-11-13",
  "assets": [
    {
      "symbol": "BTC-USD",
      "start_price": 115507.5390625,
      "end_price": 100040.390625,
      "momentum": -0.133906,
      "momentum_pct": "-13.39%"
    },
    {
      "symbol": "ETH-USD",
      "start_price": 4461.2333984375,
      "end_price": 3249.332763671875,
      "momentum": -0.271651,
      "momentum_pct": "-27.17%"
    },
    {
      "symbol": "SOL-USD",
      "start_price": 228.7561798095703,
      "end_price": 145.72683715820312,
      "momentum": -0.36296,
      "momentum_pct": "-36.30%"
    },
    {
      "symbol": "AAPL",
      "start_price": 229.80722045898438,
      "end_price": 272.95001220703125,
      "momentum": 0.187735,
      "momentum_pct": "18.77%"
    }
  ]
}