{
  "generated_at_utc": "2025-12-12T07:01:16.360291+00:00",
  "lookback_days": 60,
  "start_date": "2025-10-13",
  "end_date": "2025-12-12",
  "assets": [
    {
      "symbol": "BTC-USD",
      "start_price": 113214.3671875,
      "end_price": 92532.6171875,
      "momentum": -0.182678,
      "momentum_pct": "-18.27%"
    },
    {
      "symbol": "ETH-USD",
      "start_price": 3843.0087890625,
      "end_price": 3254.0205078125,
      "momentum": -0.153262,
      "momentum_pct": "-15.33%"
    },
    {
      "symbol": "SOL-USD",
      "start_price": 188.6638641357422,
      "end_price": 139.0173797607422,
      "momentum": -0.263148,
      "momentum_pct": "-26.31%"
    },
    {
      "symbol": "AAPL",
      "start_price": 245.032470703125,
      "end_price": 278.0299987792969,
      "momentum": 0.134666,
      "momentum_pct": "13.47%"
    }
  ]
}