{
  "generated_at_utc": "2026-04-24T08:24:00.416802+00:00",
  "lookback_days": 60,
  "start_date": "2026-02-23",
  "end_date": "2026-04-24",
  "assets": [
    {
      "symbol": "BTC-USD",
      "start_price": 68005.421875,
      "end_price": 77972.3828125,
      "momentum": 0.146561,
      "momentum_pct": "14.66%"
    },
    {
      "symbol": "ETH-USD",
      "start_price": 1969.0223388671875,
      "end_price": 2321.239990234375,
      "momentum": 0.178879,
      "momentum_pct": "17.89%"
    },
    {
      "symbol": "SOL-USD",
      "start_price": 84.6351089477539,
      "end_price": 85.66000366210938,
      "momentum": 0.01211,
      "momentum_pct": "1.21%"
    },
    {
      "symbol": "AAPL",
      "start_price": 264.5799865722656,
      "end_price": 273.42999267578125,
      "momentum": 0.033449,
      "momentum_pct": "3.34%"
    }
  ]
}