{
  "generated_at_utc": "2025-12-06T22:22:54.386417+00:00",
  "lookback_days": 60,
  "start_date": "2025-10-07",
  "end_date": "2025-12-06",
  "assets": [
    {
      "symbol": "BTC-USD",
      "start_price": 122425.4296875,
      "end_price": 89529.703125,
      "momentum": -0.2687,
      "momentum_pct": "-26.87%"
    },
    {
      "symbol": "ETH-USD",
      "start_price": 4489.197265625,
      "end_price": 3052.2119140625,
      "momentum": -0.320099,
      "momentum_pct": "-32.01%"
    },
    {
      "symbol": "SOL-USD",
      "start_price": 228.00320434570312,
      "end_price": 132.43798828125,
      "momentum": -0.41914,
      "momentum_pct": "-41.91%"
    },
    {
      "symbol": "AAPL",
      "start_price": 256.44140625,
      "end_price": 278.7799987792969,
      "momentum": 0.08711,
      "momentum_pct": "8.71%"
    }
  ]
}