{
  "generated_at_utc": "2025-12-03T10:52:11.389710+00:00",
  "lookback_days": 60,
  "start_date": "2025-10-04",
  "end_date": "2025-12-03",
  "assets": [
    {
      "symbol": "BTC-USD",
      "start_price": 118648.9296875,
      "end_price": 93012.7734375,
      "momentum": -0.216067,
      "momentum_pct": "-21.61%"
    },
    {
      "symbol": "ETH-USD",
      "start_price": 4351.1123046875,
      "end_price": 3058.8134765625,
      "momentum": -0.297004,
      "momentum_pct": "-29.70%"
    },
    {
      "symbol": "SOL-USD",
      "start_price": 221.67587280273438,
      "end_price": 141.5383758544922,
      "momentum": -0.361508,
      "momentum_pct": "-36.15%"
    },
    {
      "symbol": "AAPL",
      "start_price": 255.20260620117188,
      "end_price": 286.19000244140625,
      "momentum": 0.121423,
      "momentum_pct": "12.14%"
    }
  ]
}