{
  "generated_at_utc": "2025-11-07T13:31:44.979563+00:00",
  "lookback_days": 60,
  "start_date": "2025-09-08",
  "end_date": "2025-11-07",
  "assets": [
    {
      "symbol": "BTC-USD",
      "start_price": 110650.984375,
      "end_price": 100094.2890625,
      "momentum": -0.095405,
      "momentum_pct": "-9.54%"
    },
    {
      "symbol": "ETH-USD",
      "start_price": 4306.98876953125,
      "end_price": 3234.64697265625,
      "momentum": -0.248977,
      "momentum_pct": "-24.90%"
    },
    {
      "symbol": "SOL-USD",
      "start_price": 203.49851989746094,
      "end_price": 152.348388671875,
      "momentum": -0.251354,
      "momentum_pct": "-25.14%"
    },
    {
      "symbol": "AAPL",
      "start_price": 239.69000244140625,
      "end_price": 269.7699890136719,
      "momentum": 0.125495,
      "momentum_pct": "12.55%"
    }
  ]
}