{
  "generated_at_utc": "2026-05-14T23:00:44.149742+00:00",
  "lookback_days": 60,
  "start_date": "2026-03-15",
  "end_date": "2026-05-14",
  "assets": [
    {
      "symbol": "BTC-USD",
      "start_price": 70493.4609375,
      "end_price": 81403.953125,
      "momentum": 0.154773,
      "momentum_pct": "15.48%"
    },
    {
      "symbol": "ETH-USD",
      "start_price": 2073.13623046875,
      "end_price": 2295.8798828125,
      "momentum": 0.107443,
      "momentum_pct": "10.74%"
    },
    {
      "symbol": "SOL-USD",
      "start_price": 86.86779022216797,
      "end_price": 92.58000183105469,
      "momentum": 0.065758,
      "momentum_pct": "6.58%"
    },
    {
      "symbol": "AAPL",
      "start_price": 255.52456665039062,
      "end_price": 298.2099914550781,
      "momentum": 0.16705,
      "momentum_pct": "16.71%"
    }
  ]
}