{
  "generated_at_utc": "2025-08-17T09:23:40.915334+00:00",
  "lookback_days": 60,
  "start_date": "2025-06-18",
  "end_date": "2025-08-17",
  "assets": [
    {
      "symbol": "BTC-USD",
      "start_price": 105552.0234375,
      "end_price": 118508.453125,
      "momentum": 0.122749,
      "momentum_pct": "12.27%"
    },
    {
      "symbol": "ETH-USD",
      "start_price": 2546.837158203125,
      "end_price": 4554.611328125,
      "momentum": 0.78834,
      "momentum_pct": "78.83%"
    },
    {
      "symbol": "SOL-USD",
      "start_price": 152.81439208984375,
      "end_price": 193.03271484375,
      "momentum": 0.263184,
      "momentum_pct": "26.32%"
    },
    {
      "symbol": "AAPL",
      "start_price": 198.195068359375,
      "end_price": 231.58999633789062,
      "momentum": 0.168495,
      "momentum_pct": "16.85%"
    }
  ]
}