{
  "generated_at_utc": "2025-12-31T05:34:46.725095+00:00",
  "lookback_days": 60,
  "start_date": "2025-11-01",
  "end_date": "2025-12-31",
  "assets": [
    {
      "symbol": "BTC-USD",
      "start_price": 110055.3046875,
      "end_price": 88359.1171875,
      "momentum": -0.197139,
      "momentum_pct": "-19.71%"
    },
    {
      "symbol": "ETH-USD",
      "start_price": 3903.35302734375,
      "end_price": 2975.120361328125,
      "momentum": -0.237804,
      "momentum_pct": "-23.78%"
    },
    {
      "symbol": "SOL-USD",
      "start_price": 194.41087341308594,
      "end_price": 125.47965240478516,
      "momentum": -0.354565,
      "momentum_pct": "-35.46%"
    },
    {
      "symbol": "AAPL",
      "start_price": 269.4388122558594,
      "end_price": 273.0799865722656,
      "momentum": 0.013514,
      "momentum_pct": "1.35%"
    }
  ]
}