{
  "generated_at_utc": "2025-12-18T11:55:56.186810+00:00",
  "lookback_days": 60,
  "start_date": "2025-10-19",
  "end_date": "2025-12-18",
  "assets": [
    {
      "symbol": "BTC-USD",
      "start_price": 108186.0390625,
      "end_price": 87141.0234375,
      "momentum": -0.194526,
      "momentum_pct": "-19.45%"
    },
    {
      "symbol": "ETH-USD",
      "start_price": 3894.75439453125,
      "end_price": 2855.733642578125,
      "momentum": -0.266774,
      "momentum_pct": "-26.68%"
    },
    {
      "symbol": "SOL-USD",
      "start_price": 184.68894958496094,
      "end_price": 123.80126190185547,
      "momentum": -0.329677,
      "momentum_pct": "-32.97%"
    },
    {
      "symbol": "AAPL",
      "start_price": 247.21035766601562,
      "end_price": 271.8399963378906,
      "momentum": 0.09963,
      "momentum_pct": "9.96%"
    }
  ]
}