{
  "generated_at_utc": "2025-09-28T19:52:50.829306+00:00",
  "lookback_days": 60,
  "start_date": "2025-07-30",
  "end_date": "2025-09-28",
  "assets": [
    {
      "symbol": "BTC-USD",
      "start_price": 119448.4921875,
      "end_price": 110393.2109375,
      "momentum": -0.075809,
      "momentum_pct": "-7.58%"
    },
    {
      "symbol": "ETH-USD",
      "start_price": 3875.24658203125,
      "end_price": 4040.410400390625,
      "momentum": 0.04262,
      "momentum_pct": "4.26%"
    },
    {
      "symbol": "SOL-USD",
      "start_price": 188.73348999023438,
      "end_price": 206.3346710205078,
      "momentum": 0.093259,
      "momentum_pct": "9.33%"
    },
    {
      "symbol": "AAPL",
      "start_price": 213.80735778808594,
      "end_price": 255.4600067138672,
      "momentum": 0.194814,
      "momentum_pct": "19.48%"
    }
  ]
}