{
  "generated_at_utc": "2025-12-07T08:30:00.282288+00:00",
  "lookback_days": 60,
  "start_date": "2025-10-08",
  "end_date": "2025-12-07",
  "assets": [
    {
      "symbol": "BTC-USD",
      "start_price": 123513.4765625,
      "end_price": 89360.03125,
      "momentum": -0.276516,
      "momentum_pct": "-27.65%"
    },
    {
      "symbol": "ETH-USD",
      "start_price": 4515.4228515625,
      "end_price": 3034.2216796875,
      "momentum": -0.328032,
      "momentum_pct": "-32.80%"
    },
    {
      "symbol": "SOL-USD",
      "start_price": 228.6011962890625,
      "end_price": 131.958740234375,
      "momentum": -0.422756,
      "momentum_pct": "-42.28%"
    },
    {
      "symbol": "AAPL",
      "start_price": 256.44140625,
      "end_price": 278.7799987792969,
      "momentum": 0.08711,
      "momentum_pct": "8.71%"
    }
  ]
}