{
  "generated_at_utc": "2026-04-30T15:23:23.328927+00:00",
  "lookback_days": 60,
  "start_date": "2026-03-01",
  "end_date": "2026-04-30",
  "assets": [
    {
      "symbol": "BTC-USD",
      "start_price": 67453.7734375,
      "end_price": 76364.9765625,
      "momentum": 0.132108,
      "momentum_pct": "13.21%"
    },
    {
      "symbol": "ETH-USD",
      "start_price": 2026.7926025390625,
      "end_price": 2262.6201171875,
      "momentum": 0.116355,
      "momentum_pct": "11.64%"
    },
    {
      "symbol": "SOL-USD",
      "start_price": 85.90911865234375,
      "end_price": 83.18000030517578,
      "momentum": -0.031768,
      "momentum_pct": "-3.18%"
    },
    {
      "symbol": "AAPL",
      "start_price": 272.95001220703125,
      "end_price": 271.30499267578125,
      "momentum": -0.006027,
      "momentum_pct": "-0.60%"
    }
  ]
}