{
  "generated_at_utc": "2025-10-23T21:52:44.582008+00:00",
  "lookback_days": 60,
  "start_date": "2025-08-24",
  "end_date": "2025-10-23",
  "assets": [
    {
      "symbol": "BTC-USD",
      "start_price": 112419.03125,
      "end_price": 109605.0625,
      "momentum": -0.025031,
      "momentum_pct": "-2.50%"
    },
    {
      "symbol": "ETH-USD",
      "start_price": 4223.2099609375,
      "end_price": 3829.202880859375,
      "momentum": -0.093296,
      "momentum_pct": "-9.33%"
    },
    {
      "symbol": "SOL-USD",
      "start_price": 180.28062438964844,
      "end_price": 189.07135009765625,
      "momentum": 0.048761,
      "momentum_pct": "4.88%"
    },
    {
      "symbol": "AAPL",
      "start_price": 224.89999389648438,
      "end_price": 259.5799865722656,
      "momentum": 0.154202,
      "momentum_pct": "15.42%"
    }
  ]
}