{
  "generated_at_utc": "2025-12-21T17:21:01.200225+00:00",
  "lookback_days": 60,
  "start_date": "2025-10-22",
  "end_date": "2025-12-21",
  "assets": [
    {
      "symbol": "BTC-USD",
      "start_price": 108666.7109375,
      "end_price": 88419.5625,
      "momentum": -0.186323,
      "momentum_pct": "-18.63%"
    },
    {
      "symbol": "ETH-USD",
      "start_price": 3984.649658203125,
      "end_price": 2985.913330078125,
      "momentum": -0.250646,
      "momentum_pct": "-25.06%"
    },
    {
      "symbol": "SOL-USD",
      "start_price": 187.79820251464844,
      "end_price": 126.11996459960938,
      "momentum": -0.328428,
      "momentum_pct": "-32.84%"
    },
    {
      "symbol": "AAPL",
      "start_price": 261.98602294921875,
      "end_price": 273.6700134277344,
      "momentum": 0.044598,
      "momentum_pct": "4.46%"
    }
  ]
}