{
  "generated_at_utc": "2025-08-26T10:26:08.863736+00:00",
  "lookback_days": 60,
  "start_date": "2025-06-27",
  "end_date": "2025-08-26",
  "assets": [
    {
      "symbol": "BTC-USD",
      "start_price": 106045.6328125,
      "end_price": 110368.8359375,
      "momentum": 0.040767,
      "momentum_pct": "4.08%"
    },
    {
      "symbol": "ETH-USD",
      "start_price": 2448.0087890625,
      "end_price": 4427.38623046875,
      "momentum": 0.808566,
      "momentum_pct": "80.86%"
    },
    {
      "symbol": "SOL-USD",
      "start_price": 145.95452880859375,
      "end_price": 188.4069061279297,
      "momentum": 0.29086,
      "momentum_pct": "29.09%"
    },
    {
      "symbol": "AAPL",
      "start_price": 200.07293701171875,
      "end_price": 227.16000366210938,
      "momentum": 0.135386,
      "momentum_pct": "13.54%"
    }
  ]
}