{
  "generated_at_utc": "2026-02-09T11:33:54.070868+00:00",
  "lookback_days": 60,
  "start_date": "2025-12-11",
  "end_date": "2026-02-09",
  "assets": [
    {
      "symbol": "BTC-USD",
      "start_price": 90640.203125,
      "end_price": 68934.640625,
      "momentum": -0.239469,
      "momentum_pct": "-23.95%"
    },
    {
      "symbol": "ETH-USD",
      "start_price": 3125.197998046875,
      "end_price": 2026.85400390625,
      "momentum": -0.351448,
      "momentum_pct": "-35.14%"
    },
    {
      "symbol": "SOL-USD",
      "start_price": 133.27822875976562,
      "end_price": 83.46979522705078,
      "momentum": -0.373718,
      "momentum_pct": "-37.37%"
    },
    {
      "symbol": "AAPL",
      "start_price": 277.8900146484375,
      "end_price": 278.1199951171875,
      "momentum": 0.000828,
      "momentum_pct": "0.08%"
    }
  ]
}