{
  "generated_at_utc": "2026-01-11T21:41:23.592005+00:00",
  "lookback_days": 60,
  "start_date": "2025-11-12",
  "end_date": "2026-01-11",
  "assets": [
    {
      "symbol": "BTC-USD",
      "start_price": 104719.640625,
      "end_price": 90561.1328125,
      "momentum": -0.135204,
      "momentum_pct": "-13.52%"
    },
    {
      "symbol": "ETH-USD",
      "start_price": 3582.621337890625,
      "end_price": 3110.615966796875,
      "momentum": -0.131749,
      "momentum_pct": "-13.17%"
    },
    {
      "symbol": "SOL-USD",
      "start_price": 164.45384216308594,
      "end_price": 138.14584350585938,
      "momentum": -0.159972,
      "momentum_pct": "-16.00%"
    },
    {
      "symbol": "AAPL",
      "start_price": 269.42999267578125,
      "end_price": 259.3699951171875,
      "momentum": -0.037338,
      "momentum_pct": "-3.73%"
    }
  ]
}