{
  "generated_at_utc": "2025-11-18T13:55:27.238744+00:00",
  "lookback_days": 60,
  "start_date": "2025-09-19",
  "end_date": "2025-11-18",
  "assets": [
    {
      "symbol": "BTC-USD",
      "start_price": 116843.1875,
      "end_price": 91215.90625,
      "momentum": -0.219331,
      "momentum_pct": "-21.93%"
    },
    {
      "symbol": "ETH-USD",
      "start_price": 4503.564453125,
      "end_price": 3039.4990234375,
      "momentum": -0.32509,
      "momentum_pct": "-32.51%"
    },
    {
      "symbol": "SOL-USD",
      "start_price": 236.9895782470703,
      "end_price": 137.8113250732422,
      "momentum": -0.418492,
      "momentum_pct": "-41.85%"
    },
    {
      "symbol": "AAPL",
      "start_price": 237.9193572998047,
      "end_price": 267.4599914550781,
      "momentum": 0.124162,
      "momentum_pct": "12.42%"
    }
  ]
}