{
  "generated_at_utc": "2025-12-25T19:40:10.486720+00:00",
  "lookback_days": 60,
  "start_date": "2025-10-26",
  "end_date": "2025-12-25",
  "assets": [
    {
      "symbol": "BTC-USD",
      "start_price": 110069.7265625,
      "end_price": 88058.390625,
      "momentum": -0.199976,
      "momentum_pct": "-20.00%"
    },
    {
      "symbol": "ETH-USD",
      "start_price": 3856.0263671875,
      "end_price": 2952.346923828125,
      "momentum": -0.234355,
      "momentum_pct": "-23.44%"
    },
    {
      "symbol": "SOL-USD",
      "start_price": 191.38827514648438,
      "end_price": 123.51905822753906,
      "momentum": -0.354615,
      "momentum_pct": "-35.46%"
    },
    {
      "symbol": "AAPL",
      "start_price": 259.3285827636719,
      "end_price": 273.80999755859375,
      "momentum": 0.055842,
      "momentum_pct": "5.58%"
    }
  ]
}