{
  "generated_at_utc": "2025-10-03T07:52:38.045568+00:00",
  "lookback_days": 60,
  "start_date": "2025-08-04",
  "end_date": "2025-10-03",
  "assets": [
    {
      "symbol": "BTC-USD",
      "start_price": 113320.0859375,
      "end_price": 119796.015625,
      "momentum": 0.057147,
      "momentum_pct": "5.71%"
    },
    {
      "symbol": "ETH-USD",
      "start_price": 3488.365966796875,
      "end_price": 4463.9296875,
      "momentum": 0.279662,
      "momentum_pct": "27.97%"
    },
    {
      "symbol": "SOL-USD",
      "start_price": 162.87709045410156,
      "end_price": 229.26400756835938,
      "momentum": 0.407589,
      "momentum_pct": "40.76%"
    },
    {
      "symbol": "AAPL",
      "start_price": 202.1505889892578,
      "end_price": 257.1300048828125,
      "momentum": 0.271973,
      "momentum_pct": "27.20%"
    }
  ]
}