{
  "generated_at_utc": "2025-09-14T05:40:01.615391+00:00",
  "lookback_days": 60,
  "start_date": "2025-07-16",
  "end_date": "2025-09-14",
  "assets": [
    {
      "symbol": "BTC-USD",
      "start_price": 119116.1171875,
      "end_price": 115935.0546875,
      "momentum": -0.026706,
      "momentum_pct": "-2.67%"
    },
    {
      "symbol": "ETH-USD",
      "start_price": 2973.35888671875,
      "end_price": 4681.0146484375,
      "momentum": 0.574319,
      "momentum_pct": "57.43%"
    },
    {
      "symbol": "SOL-USD",
      "start_price": 161.1940155029297,
      "end_price": 247.2317352294922,
      "momentum": 0.533753,
      "momentum_pct": "53.38%"
    },
    {
      "symbol": "AAPL",
      "start_price": 208.3834991455078,
      "end_price": 234.07000732421875,
      "momentum": 0.123266,
      "momentum_pct": "12.33%"
    }
  ]
}