{
  "generated_at_utc": "2025-08-28T08:51:01.044202+00:00",
  "lookback_days": 60,
  "start_date": "2025-06-29",
  "end_date": "2025-08-28",
  "assets": [
    {
      "symbol": "BTC-USD",
      "start_price": 106960.0,
      "end_price": 113309.0078125,
      "momentum": 0.059359,
      "momentum_pct": "5.94%"
    },
    {
      "symbol": "ETH-USD",
      "start_price": 2416.146728515625,
      "end_price": 4610.609375,
      "momentum": 0.908249,
      "momentum_pct": "90.82%"
    },
    {
      "symbol": "SOL-USD",
      "start_price": 139.0598602294922,
      "end_price": 214.08975219726562,
      "momentum": 0.539551,
      "momentum_pct": "53.96%"
    },
    {
      "symbol": "AAPL",
      "start_price": 200.7721405029297,
      "end_price": 230.49000549316406,
      "momentum": 0.148018,
      "momentum_pct": "14.80%"
    }
  ]
}