{
  "generated_at_utc": "2025-08-23T13:52:48.274773+00:00",
  "lookback_days": 60,
  "start_date": "2025-06-24",
  "end_date": "2025-08-23",
  "assets": [
    {
      "symbol": "BTC-USD",
      "start_price": 102257.40625,
      "end_price": 115015.1171875,
      "momentum": 0.124761,
      "momentum_pct": "12.48%"
    },
    {
      "symbol": "ETH-USD",
      "start_price": 2300.49560546875,
      "end_price": 4724.0615234375,
      "momentum": 1.053497,
      "momentum_pct": "105.35%"
    },
    {
      "symbol": "SOL-USD",
      "start_price": 135.1610107421875,
      "end_price": 201.60751342773438,
      "momentum": 0.49161,
      "momentum_pct": "49.16%"
    },
    {
      "symbol": "AAPL",
      "start_price": 201.27157592773438,
      "end_price": 227.75999450683594,
      "momentum": 0.131605,
      "momentum_pct": "13.16%"
    }
  ]
}