{
  "generated_at_utc": "2025-09-21T12:41:35.826177+00:00",
  "lookback_days": 60,
  "start_date": "2025-07-23",
  "end_date": "2025-09-21",
  "assets": [
    {
      "symbol": "BTC-USD",
      "start_price": 117300.7890625,
      "end_price": 115785.3125,
      "momentum": -0.01292,
      "momentum_pct": "-1.29%"
    },
    {
      "symbol": "ETH-USD",
      "start_price": 3759.471435546875,
      "end_price": 4473.8564453125,
      "momentum": 0.190023,
      "momentum_pct": "19.00%"
    },
    {
      "symbol": "SOL-USD",
      "start_price": 181.54603576660156,
      "end_price": 239.95684814453125,
      "momentum": 0.321741,
      "momentum_pct": "32.17%"
    },
    {
      "symbol": "AAPL",
      "start_price": 212.23912048339844,
      "end_price": 245.5,
      "momentum": 0.156714,
      "momentum_pct": "15.67%"
    }
  ]
}