{
  "generated_at_utc": "2025-11-24T11:53:42.724447+00:00",
  "lookback_days": 60,
  "start_date": "2025-09-25",
  "end_date": "2025-11-24",
  "assets": [
    {
      "symbol": "BTC-USD",
      "start_price": 112748.5078125,
      "end_price": 86296.40625,
      "momentum": -0.234612,
      "momentum_pct": "-23.46%"
    },
    {
      "symbol": "ETH-USD",
      "start_price": 4202.87744140625,
      "end_price": 2802.885009765625,
      "momentum": -0.333103,
      "momentum_pct": "-33.31%"
    },
    {
      "symbol": "SOL-USD",
      "start_price": 220.49644470214844,
      "end_price": 129.65435791015625,
      "momentum": -0.411989,
      "momentum_pct": "-41.20%"
    },
    {
      "symbol": "AAPL",
      "start_price": 255.8319854736328,
      "end_price": 271.489990234375,
      "momentum": 0.061204,
      "momentum_pct": "6.12%"
    }
  ]
}