{
  "generated_at_utc": "2025-11-07T22:53:59.496730+00:00",
  "lookback_days": 60,
  "start_date": "2025-09-08",
  "end_date": "2025-11-07",
  "assets": [
    {
      "symbol": "BTC-USD",
      "start_price": 110650.984375,
      "end_price": 103754.75,
      "momentum": -0.062324,
      "momentum_pct": "-6.23%"
    },
    {
      "symbol": "ETH-USD",
      "start_price": 4306.98876953125,
      "end_price": 3452.40625,
      "momentum": -0.198418,
      "momentum_pct": "-19.84%"
    },
    {
      "symbol": "SOL-USD",
      "start_price": 203.49851989746094,
      "end_price": 163.25619506835938,
      "momentum": -0.197752,
      "momentum_pct": "-19.78%"
    },
    {
      "symbol": "AAPL",
      "start_price": 239.69000244140625,
      "end_price": 268.4700012207031,
      "momentum": 0.120072,
      "momentum_pct": "12.01%"
    }
  ]
}