{
  "generated_at_utc": "2026-02-05T11:03:22.737864+00:00",
  "lookback_days": 60,
  "start_date": "2025-12-07",
  "end_date": "2026-02-05",
  "assets": [
    {
      "symbol": "BTC-USD",
      "start_price": 92141.625,
      "end_price": 70730.5859375,
      "momentum": -0.232371,
      "momentum_pct": "-23.24%"
    },
    {
      "symbol": "ETH-USD",
      "start_price": 3134.31640625,
      "end_price": 2093.613525390625,
      "momentum": -0.332035,
      "momentum_pct": "-33.20%"
    },
    {
      "symbol": "SOL-USD",
      "start_price": 139.0145263671875,
      "end_price": 90.14212799072266,
      "momentum": -0.351563,
      "momentum_pct": "-35.16%"
    },
    {
      "symbol": "AAPL",
      "start_price": 280.70001220703125,
      "end_price": 276.489990234375,
      "momentum": -0.014998,
      "momentum_pct": "-1.50%"
    }
  ]
}