{
  "generated_at_utc": "2026-03-13T09:45:54.853094+00:00",
  "lookback_days": 60,
  "start_date": "2026-01-12",
  "end_date": "2026-03-13",
  "assets": [
    {
      "symbol": "BTC-USD",
      "start_price": 90513.1015625,
      "end_price": 71865.3984375,
      "momentum": -0.206022,
      "momentum_pct": "-20.60%"
    },
    {
      "symbol": "ETH-USD",
      "start_price": 3083.047119140625,
      "end_price": 2106.3232421875,
      "momentum": -0.316805,
      "momentum_pct": "-31.68%"
    },
    {
      "symbol": "SOL-USD",
      "start_price": 135.7563934326172,
      "end_price": 89.2415771484375,
      "momentum": -0.342634,
      "momentum_pct": "-34.26%"
    },
    {
      "symbol": "AAPL",
      "start_price": 259.1275329589844,
      "end_price": 255.75999450683594,
      "momentum": -0.012996,
      "momentum_pct": "-1.30%"
    }
  ]
}