{
  "generated_at_utc": "2026-06-07T18:49:20.908266+00:00",
  "lookback_days": 60,
  "start_date": "2026-04-08",
  "end_date": "2026-06-07",
  "assets": [
    {
      "symbol": "BTC-USD",
      "start_price": 68981.8984375,
      "end_price": 62177.66015625,
      "momentum": -0.098638,
      "momentum_pct": "-9.86%"
    },
    {
      "symbol": "ETH-USD",
      "start_price": 2108.99560546875,
      "end_price": 1633.800048828125,
      "momentum": -0.225318,
      "momentum_pct": "-22.53%"
    },
    {
      "symbol": "SOL-USD",
      "start_price": 81.8544921875,
      "end_price": 65.25,
      "momentum": -0.202854,
      "momentum_pct": "-20.29%"
    },
    {
      "symbol": "AAPL",
      "start_price": 258.6217041015625,
      "end_price": 307.3399963378906,
      "momentum": 0.188377,
      "momentum_pct": "18.84%"
    }
  ]
}