{
  "generated_at_utc": "2025-12-02T19:01:16.750297+00:00",
  "lookback_days": 60,
  "start_date": "2025-10-03",
  "end_date": "2025-12-02",
  "assets": [
    {
      "symbol": "BTC-USD",
      "start_price": 114056.0859375,
      "end_price": 91825.796875,
      "momentum": -0.194907,
      "momentum_pct": "-19.49%"
    },
    {
      "symbol": "ETH-USD",
      "start_price": 4145.95751953125,
      "end_price": 3011.38671875,
      "momentum": -0.273657,
      "momentum_pct": "-27.37%"
    },
    {
      "symbol": "SOL-USD",
      "start_price": 208.7431182861328,
      "end_price": 139.80160522460938,
      "momentum": -0.33027,
      "momentum_pct": "-33.03%"
    },
    {
      "symbol": "AAPL",
      "start_price": 254.38340759277344,
      "end_price": 285.190185546875,
      "momentum": 0.121104,
      "momentum_pct": "12.11%"
    }
  ]
}